AdroitComs/AdroitComs.py
AdroitComs/Constants.py
AdroitComs/Drive.py
AdroitComs/Util.py
AdroitComs/__init__.py
AdroitComs-0.0.1.dist-info/METADATA
AdroitComs-0.0.1.dist-info/WHEEL
AdroitComs-0.0.1.dist-info/top_level.txt
AdroitComs-0.0.1.dist-info/RECORD
