Metadata-Version: 2.1
Name: AdroitComs
Version: 0.0.1
Summary: A package for communicating with HDT Adroit robots over CAN.
Home-page: UNKNOWN
Author: Cameron Devine
Author-email: camdev@uw.edu
License: UNKNOWN
Platform: UNKNOWN
Requires-Python: >=3.6
Requires-Dist: numpy
Requires-Dist: python-can
